img2txtio/__init__.py
img2txtio/main.py
img2txtio-0.0.4.dist-info/licenses/LICENSE
img2txtio-0.0.4.dist-info/METADATA
img2txtio-0.0.4.dist-info/WHEEL
img2txtio-0.0.4.dist-info/top_level.txt
img2txtio-0.0.4.dist-info/RECORD
