Metadata-Version: 2.4
Name: img2txtio
Version: 0.0.4
Summary: A simple SDK for using the Img2Txt API.
Author-email: Ben Webster <ben@wbxdigital.com>
Project-URL: Homepage, https://img2txt.io
Project-URL: Issues, https://img2txt.io/#contact
Classifier: Programming Language :: Python :: 3
Classifier: Operating System :: OS Independent
Requires-Python: >=3.12
License-File: LICENSE
Requires-Dist: requests>=2.32.4
Dynamic: license-file
